Protoss_Pylon
Protoss_Gateway
Protoss_Assimilator
Protoss_Cybernetics_Core
Protoss_Robotics_Facility
Protoss_Robotics_Support_Bay
Protoss_Pylon
Protoss_Gateway
Protoss_Observatory
Protoss_Forge
Protoss_Photon_Cannon
Protoss_Photon_Cannon
Protoss_Gateway
Protoss_Nexus
Protoss_Robotics_Facility
Protoss_Gateway
Protoss_Pylon
Protoss_Citadel_of_Adun
Protoss_Templar_Archives
Protoss_Nexus
Protoss_Gateway
Protoss_Photon_Cannon
Protoss_Pylon
Protoss_Stargate
Protoss_Arbiter_Tribunal
Protoss_Pylon
Protoss_Photon_Cannon
Protoss_Gateway
Protoss_Nexus
Protoss_Stargate
Protoss_Photon_Cannon
Protoss_Pylon
Protoss_Photon_Cannon
Protoss_Shield_Battery
Protoss_Fleet_Beacon