Zerg_Spawning_Pool
Zerg_Hatchery
Zerg_Extractor
Zerg_Hydralisk_Den
Zerg_Hatchery
Zerg_Evolution_Chamber
Zerg_Extractor
Zerg_Creep_Colony
Zerg_Sunken_Colony
Zerg_Hatchery
Zerg_Extractor
Zerg_Creep_Colony
Zerg_Sunken_Colony
Zerg_Hatchery
Zerg_Queens_Nest
Zerg_Hatchery
Zerg_Extractor
Zerg_Creep_Colony
Zerg_Sunken_Colony
Zerg_Ultralisk_Cavern
Zerg_Hatchery
Zerg_Creep_Colony
Zerg_Sunken_Colony









