Zerg_Spawning_Pool
Zerg_Extractor
Zerg_Hatchery
Zerg_Hydralisk_Den
Zerg_Hatchery
Zerg_Evolution_Chamber
Zerg_Extractor
Zerg_Spire
Zerg_Queens_Nest
Zerg_Hatchery
Zerg_Defiler_Mound
Zerg_Extractor
Zerg_Hatchery
Zerg_Evolution_Chamber
Zerg_Hatchery
Zerg_Extractor




















